<Properties StartupConfiguration="{1ADAFD7C-186E-74BB-F621-9D3BD15AF105}|">
  <MonoDevelop.Ide.Workbench ActiveDocument="Assets/Scripts/Manager.cs">
    <Files>
      <File FileName="Assets/Scripts/Dude.cs" Line="65" Column="26" />
      <File FileName="Assets/Scripts/Launcher.cs" Line="211" Column="20" />
      <File FileName="Assets/Scripts/Manager.cs" Line="18" Column="14" />
      <File FileName="Assets/Scripts/LevelActivator.cs" Line="13" Column="43" />
    </Files>
    <Pads>
      <Pad Id="ProjectPad">
        <State name="__root__">
          <Node name="Cannonball Engineers" expanded="True">
            <Node name="Assets" expanded="True">
              <Node name="Effects" expanded="True" />
              <Node name="Scripts" expanded="True">
                <Node name="Manager.cs" selected="True" />
              </Node>
              <Node name="Splats" expanded="True" />
            </Node>
          </Node>
        </State>
      </Pad>
    </Pads>
  </MonoDevelop.Ide.Workbench>
  <MonoDevelop.Ide.DebuggingService.PinnedWatches />
  <MonoDevelop.Ide.Workspace ActiveConfiguration="Debug" />
  <MonoDevelop.Ide.ItemProperties.Assembly-CSharp PreferredExecutionTarget="0a55043e-2bfb-449a-a825-71e2df47a2f1" />
  <MonoDevelop.Ide.DebuggingService.Breakpoints>
    <BreakpointStore />
  </MonoDevelop.Ide.DebuggingService.Breakpoints>
  <MultiItemStartupConfigurations />
</Properties>